websockets/speedups.cpython-310-x86_64-linux-gnu.so
mahsocket-0.0.1.dist-info/LICENSE
mahsocket-0.0.1.dist-info/METADATA
mahsocket-0.0.1.dist-info/WHEEL
mahsocket-0.0.1.dist-info/top_level.txt
mahsocket-0.0.1.dist-info/RECORD
